{
    "event_annotation": [
        {
            "start": "1826",
            "end": "2859",
            "type": "Normal"
        },
        {
            "start": "3236",
            "end": "4853",
            "type": "Normal"
        },
        {
            "start": "11308",
            "end": "12092",
            "type": "Normal"
        },
        {
            "start": "14418",
            "end": "15237",
            "type": "Wheeze"
        },
        {
            "start": "12181",
            "end": "12978",
            "type": "Wheeze"
        }
    ]
}