{
    "event_annotation": [
        {
            "start": "5528",
            "end": "7100",
            "type": "Normal"
        },
        {
            "start": "1272",
            "end": "3094",
            "type": "Normal"
        },
        {
            "start": "3497",
            "end": "5058",
            "type": "Normal"
        },
        {
            "start": "7677",
            "end": "9258",
            "type": "Normal"
        },
        {
            "start": "10255",
            "end": "12428",
            "type": "Normal"
        }
    ]
}